{
    "InnerArray": [
        {
            "Id": 1,
            "EventContentsType": "ScreenImages",
            "Arg": [
                "Tutorial1,Tutorial2"
            ]
        },
        { 
            "Id": 2,
            "EventContentsType": "ScreenImages",
            "Arg": [
                "Tutorial7"
            ]
        },
        { 
            "Id": 3,
            "EventContentsType": "Nope",
            "Arg": [
            ]
        },
        { 
            "Id": 4,
            "EventContentsType": "ForceConversation",
            "Arg": [
                1
            ]
        },
        { 
            "Id": 5,
            "EventContentsType": "ForceConversation",
            "Arg": [
                2
            ]
        },
        { 
            "Id": 6,
            "EventContentsType": "ForceConversation",
            "Arg": [
                3
            ]
        },
        { 
            "Id": 7,
            "EventContentsType": "ForceConversation",
            "Arg": [
                4
            ]
        },
        { 
            "Id": 8,
            "EventContentsType": "ForceConversation",
            "Arg": [
                5
            ]
        },
        { 
            "Id": 9,
            "EventContentsType": "AppearConversationCharacterNormal",
            "Arg": [
                1,
                6,
                6,
                0.4
            ]
        },
        { 
            "Id": 10,
            "EventContentsType": "AppearConversationCharacterNormal",
            "Arg": [
                2,
                7,
                6,
                0.4
            ]
        },
        { 
            "Id": 11,
            "EventContentsType": "AppearConversationCharacterNormal",
            "Arg": [
                2,
                8,
                6,
                0.4
            ]
        },
        { 
            "Id": 12,
            "EventContentsType": "AppearConversationCharacterNormal",
            "Arg": [
                1,
                9,
                6,
                0.4
            ]
        },
        { 
            "Id": 13,
            "EventContentsType": "AppearConversationCharacterNormal",
            "Arg": [
                2,
                10,
                6,
                0.4
            ]
        },
        { 
            "Id": 14,
            "EventContentsType": "OpenParkOpen",
            "Arg": [
                4
            ]
        }
    ]
}